vnpy_da/__init__.py
vnpy_da/da_gateway.py
vnpy_da/terminal_info_linux.py
vnpy_da/terminal_info_windows.py
vnpy_da-1.18.2.5.2.dist-info/METADATA
vnpy_da-1.18.2.5.2.dist-info/WHEEL
vnpy_da-1.18.2.5.2.dist-info/licenses/LICENSE
vnpy_da-1.18.2.5.2.dist-info/RECORD
